napari_laber_manager/__init__.py
napari_laber_manager/_version.py
napari_laber_manager/_widget.py
napari_laber_manager/napari.yaml
napari_laber_manager/_tests/__init__.py
napari_laber_manager/_tests/test_widget.py
napari_laber_manager-0.0.8.dist-info/licenses/LICENSE
napari_laber_manager-0.0.8.dist-info/METADATA
napari_laber_manager-0.0.8.dist-info/WHEEL
napari_laber_manager-0.0.8.dist-info/entry_points.txt
napari_laber_manager-0.0.8.dist-info/top_level.txt
napari_laber_manager-0.0.8.dist-info/RECORD
