Metadata-Version: 2.4
Name: napari-laber-manager
Version: 0.0.8
Summary: A plugin for management of label colormap generation and opacity control
Author: JH Wang
Author-email: wjh19937458882@mail.ustc.edu.cn
License: 
Project-URL: Bug Tracker, https://github.com/Wenlab/napari-label-manager/issues
Project-URL: Documentation, https://github.com/Wenlab/napari-label-manager#README.md
Project-URL: Source Code, https://github.com/Wenlab/napari-label-manager
Project-URL: User Support, https://github.com/Wenlab/napari-label-manager/issues
Classifier: Development Status :: 2 - Pre-Alpha
Classifier: Framework :: napari
Classifier: Intended Audience :: Developers
Classifier: License :: OSI Approved :: BSD License
Classifier: Operating System :: OS Independent
Classifier: Programming Language :: Python
Classifier: Programming Language :: Python :: 3
Classifier: Programming Language :: Python :: 3 :: Only
Classifier: Programming Language :: Python :: 3.9
Classifier: Programming Language :: Python :: 3.10
Classifier: Programming Language :: Python :: 3.11
Classifier: Programming Language :: Python :: 3.12
Classifier: Topic :: Scientific/Engineering :: Image Processing
Requires-Python: >=3.9
License-File: LICENSE
Requires-Dist: numpy
Requires-Dist: magicgui
Requires-Dist: qtpy
Requires-Dist: scikit-image
Provides-Extra: all
Requires-Dist: napari[all]; extra == "all"
Provides-Extra: testing
Requires-Dist: tox; extra == "testing"
Requires-Dist: pytest; extra == "testing"
Requires-Dist: pytest-cov; extra == "testing"
Requires-Dist: pytest-qt; extra == "testing"
Requires-Dist: napari[qt]; extra == "testing"
Dynamic: license-file
